itext2kg/__init__.py
itext2kg/itext2kg.py
itext2kg/itext2kg_star.py
itext2kg/logging_config.py
itext2kg/documents_distiller/__init__.py
itext2kg/documents_distiller/documents_distiller.py
itext2kg/graph_integration/__init__.py
itext2kg/graph_integration/neo4j_storage.py
itext2kg/graph_matching/__init__.py
itext2kg/graph_matching/matcher.py
itext2kg/graph_matching/matcher_interface.py
itext2kg/ientities_extraction/__init__.py
itext2kg/ientities_extraction/ientities_extractor.py
itext2kg/irelations_extraction/__init__.py
itext2kg/irelations_extraction/irelations_extractor.py
itext2kg/irelations_extraction/simple_direct_irelations_extractor.py
itext2kg/llm_output_parsing/__init__.py
itext2kg/llm_output_parsing/langchain_output_parser.py
itext2kg/llm_output_parsing/llm_output_parser_interface.py
itext2kg/models/__init__.py
itext2kg/models/knowledge_graph.py
itext2kg/models/schemas.py
itext2kg-0.0.9.dist-info/licenses/LICENSE
tests/__init__.py
tests/test_itext2kg.py
tests/test_matcher.py
itext2kg-0.0.9.dist-info/METADATA
itext2kg-0.0.9.dist-info/WHEEL
itext2kg-0.0.9.dist-info/top_level.txt
itext2kg-0.0.9.dist-info/zip-safe
itext2kg-0.0.9.dist-info/RECORD
