Metadata-Version: 2.4
Name: itext2kg
Version: 0.0.9
Summary: Incremental Knowledge Graphs Constructor Using Large Language Models
Author: Auvalab - Yassir LAIRGI
Author-email: <yassir.lairgi@auvalie.com>
Keywords: kg construction,llms,neo4j,graphs
Classifier: Development Status :: 4 - Beta
Classifier: Intended Audience :: Developers
Classifier: Programming Language :: Python :: 3
Classifier: Programming Language :: Python :: 3.10
Classifier: Programming Language :: Python :: 3.11
Classifier: Programming Language :: Python :: 3.12
Classifier: Operating System :: Unix
Classifier: Operating System :: MacOS :: MacOS X
Classifier: Operating System :: Microsoft :: Windows
Requires-Python: >=3.10
License-File: LICENSE
Requires-Dist: langchain<0.4.0,>=0.3.26
Requires-Dist: langchain-core<0.4.0,>=0.3.69
Requires-Dist: langchain-openai<0.3.0,>=0.2.0
Requires-Dist: neo4j<6.0.0,>=5.28.0
Requires-Dist: openai<2.0.0,>=1.97.0
Requires-Dist: numpy<2.0.0,>=1.24.0
Requires-Dist: scikit-learn<2.0.0,>=1.7.0
Requires-Dist: openpyxl<4.0.0,>=3.1.0
Requires-Dist: pypdf<5.0.0,>=4.3.0
Requires-Dist: tiktoken<1.0.0,>=0.8.0
Requires-Dist: python-dateutil<3.0.0,>=2.8.0
Requires-Dist: pydantic<3.0.0,>=2.11.0
Requires-Dist: pydantic-settings<3.0.0,>=2.6.0
Dynamic: license-file
